d8s_python/__init__.py
d8s_python/ast_data.py
d8s_python/python_data.py
tests/__init__.py
tests/test_ast_data.py
tests/test_python_data.py
d8s_python-0.9.0.dist-info/COPYING
d8s_python-0.9.0.dist-info/COPYING.LESSER
d8s_python-0.9.0.dist-info/METADATA
d8s_python-0.9.0.dist-info/WHEEL
d8s_python-0.9.0.dist-info/top_level.txt
d8s_python-0.9.0.dist-info/zip-safe
d8s_python-0.9.0.dist-info/RECORD
