Metadata-Version: 2.1
Name: d8s-python
Version: 0.9.0
Summary: Democritus functions for working with Python code.
Home-page: https://github.com/democritus-project/d8s-python
Author: Floyd Hightower
Author-email: floyd.hightower27@gmail.com
License: GNU Lesser General Public License v3
Keywords: democritus,utility,python,python-asts,python-asts-utility,ast,python-ast,abstract-syntax-tree
Platform: UNKNOWN
Classifier: Development Status :: 2 - Pre-Alpha
Classifier: Intended Audience :: Developers
Classifier: License :: OSI Approved :: GNU Lesser General Public License v3 or later (LGPLv3+)
Classifier: Natural Language :: English
Classifier: Programming Language :: Python :: 3
Classifier: Programming Language :: Python :: 3.4
Classifier: Programming Language :: Python :: 3.5
Classifier: Programming Language :: Python :: 3.6
Classifier: Programming Language :: Python :: 3.7
Classifier: Programming Language :: Python :: 3.8
Classifier: Programming Language :: Python :: 3.9
Requires-Dist: d8s-algorithms (==0.*)
Requires-Dist: d8s-lists (==0.*)
Requires-Dist: d8s-strings (==0.*)
Requires-Dist: d8s-file-system (==0.*)
Requires-Dist: d8s-grammars (==0.*)
Requires-Dist: jinja2
Requires-Dist: more-itertools
Requires-Dist: importlib-metadata ; python_version < "3.8"
